{
  "tags" : [ ],
  "slug" : "Mark-11-King-Has-Come",
  "series" : "FIX_SERIES",
  "has-audio-error" : false,
  "type" : "Sermon",
  "title" : "The King Has Come",
  "scripture" : [ {
    "gte" : 41011001,
    "lte" : 41011025
  } ],
  "has-audio" : true,
  "speaker" : "Matt McCullough",
  "blurb" : "Chapter 11 marks Jesus’s arrival at Jersalem, an event laced through with prophecy fulfillment. Here, by an “enacted parable” and by a dramatic confrontation in the Temple, Jesus shows more of what he’s come to do. As King, he’s come to purge and to restore.",
  "published" : true
}