{
  "tags" : [ ],
  "slug" : "Heb-13-The-Grateful-Life",
  "series" : "FIX_SERIES",
  "has-audio-error" : false,
  "type" : "Sermon",
  "title" : "The Grateful Life",
  "scripture" : [ {
    "gte" : 58013001,
    "lte" : 58013006
  } ],
  "has-audio" : true,
  "speaker" : "Matt McCullough",
  "blurb" : "Because of Jesus, worship looks different. There are no more temples, sacrifices, or ceremonial cleansings; now worship is a way of life, a life defined by gratitude for what God has done and will do for us through Jesus. This passage gives examples of what should mark a grateful life.",
  "published" : true
}